rtl/counter.v
`timescale 1 ns / 1 ps

module counter #(
    parameter CNT_WIDTH = 8
)(
    input  logic osc_i,
    input  logic reset_cnt_i,
    output logic [CNT_WIDTH-1:0] cnt_o
);

always_ff @(posedge osc_i or posedge reset_cnt_i) begin
    if (reset_cnt_i)
        cnt_o <= '0;
    else if (cnt_o != {CNT_WIDTH{1'b1}}) // clamp at max value
        cnt_o <= cnt_o + 1;
end

endmodule

rtl/counter_tb.v
`timescale 1 ns / 1 ps

module counter_tb;
    // save data for waveform viewer
    initial begin
        $dumpfile("../sim/LELO_GR02/counter_tb_sim.vcd");
        $dumpvars(0, counter_tb);
    end

    parameter CNT_WIDTH = 4;

    logic clk;
    logic reset;
    logic [CNT_WIDTH-1:0] cnt;

    // DUT
    counter #(.CNT_WIDTH(CNT_WIDTH)) dut (
        .osc_i(clk),
        .reset_cnt_i(reset),
        .cnt_o(cnt)
    );

    initial clk = 0;
    always #1 clk = ~clk;

    integer i;

    initial begin
        $display("+++ TESTING COUNTER +++");

        // RESET TEST
        reset = 1;
        #10;
        reset = 0;

        if (cnt !== 0)
            $display("FAIL: Did not reset cnt. cnt=%0d", cnt);
        else
            $display("PASS: Reset OK");

        // COUNTING TEST
        for (i = 0; i < (1 << CNT_WIDTH); i = i + 1) begin
            @(posedge clk);
            if (cnt !== i)
                $display("FAIL: Counting failed. Expected=%0d got=%0d", i, cnt);
        end
        $display("PASS: Counting OK");

        // CLAMPING TEST
        repeat (3) @(posedge clk); // wait 3 cycles

        if (cnt !== {CNT_WIDTH{1'b1}})
            $display("FAIL: Clamping failed. cnt=%0d", cnt);
        else
            $display("PASS: Clamping OK (at %0d)", cnt);

        // RESET TEST 2
        reset = 1;
        @(posedge clk);
        reset = 0;

        if (cnt !== 0)
            $display("FAIL: Reset after counting failed. cnt=%0d", cnt);
        else
            $display("PASS: Reset after counting OK");

        $display("+++ TESTING COUNTER DONE +++");
        $finish;
    end

endmodule

sim/LELO_GR02/counter_tb_sim.vcd
$date
	Sat Mar 21 18:05:14 2026
$end
$version
	Icarus Verilog
$end
$timescale
	1ps
$end
$scope module counter_tb $end
$var wire 4 ! cnt [3:0] $end
$var parameter 32 " CNT_WIDTH $end
$var reg 1 # clk $end
$var reg 1 $ reset $end
$var integer 32 % i [31:0] $end
$scope module dut $end
$var wire 1 # osc_i $end
$var wire 1 $ reset_cnt_i $end
$var parameter 32 & CNT_WIDTH $end
$var reg 4 ' cnt_o [3:0] $end
$upscope $end
$upscope $end
$enddefinitions $end
$comment Show the parameter values. $end
$dumpall
b100 &
b100 "
$end
#0
$dumpvars
b0 '
bx %
1$
0#
b0 !
$end
#1000
1#
#2000
0#
#3000
1#
#4000
0#
#5000
1#
#6000
0#
#7000
1#
#8000
0#
#9000
1#
#10000
0#
b0 %
0$
#11000
b1 !
b1 '
b1 %
1#
#12000
0#
#13000
b10 !
b10 '
b10 %
1#
#14000
0#
#15000
b11 !
b11 '
b11 %
1#
#16000
0#
#17000
b100 !
b100 '
b100 %
1#
#18000
0#
#19000
b101 !
b101 '
b101 %
1#
#20000
0#
#21000
b110 !
b110 '
b110 %
1#
#22000
0#
#23000
b111 !
b111 '
b111 %
1#
#24000
0#
#25000
b1000 !
b1000 '
b1000 %
1#
#26000
0#
#27000
b1001 !
b1001 '
b1001 %
1#
#28000
0#
#29000
b1010 !
b1010 '
b1010 %
1#
#30000
0#
#31000
b1011 !
b1011 '
b1011 %
1#
#32000
0#
#33000
b1100 !
b1100 '
b1100 %
1#
#34000
0#
#35000
b1101 !
b1101 '
b1101 %
1#
#36000
0#
#37000
b1110 !
b1110 '
b1110 %
1#
#38000
0#
#39000
b1111 !
b1111 '
b1111 %
1#
#40000
0#
#41000
b10000 %
1#
#42000
0#
#43000
1#
#44000
0#
#45000
1#
#46000
0#
#47000
b0 !
b0 '
1$
1#
#48000
0#
#49000
b1 !
b1 '
0$
1#
