rtl/counter.v
`timescale 1 ns / 1 ps

module counter #(
    parameter CNT_WIDTH = 8
)(
    input  logic osc_i,
    input  logic reset_cnt_i,
    output logic [CNT_WIDTH-1:0] cnt_o
);

always_ff @(posedge osc_i or posedge reset_cnt_i) begin
    if (reset_cnt_i)
        cnt_o <= '0;
    else if (cnt_o != {CNT_WIDTH{1'b1}}) // clamp at max value
        cnt_o <= cnt_o + 1;
end

endmodule

rtl/fsm.v
`timescale 1 ns / 1 ps

module counter_fsm #(
    parameter CNT_WIDTH = 8
)(
    input logic clk,
    input logic rst_n,
    input logic start_i,
    input logic [CNT_WIDTH-1:0] cnt_i,
    output logic pwrup_osc_o,
    output logic reset_cnt_o, 
    output logic completed_o,  
    output logic [CNT_WIDTH-1:0] clk_cycles_o
);

// Assigning state names to binary values
// DO NOT UPDATE WITHOUT CHANGING ASSERTION OF completed_o SIGNAL
localparam IDLE    = 2'b00;
localparam CNT     = 2'b01;
localparam CAPTURE = 2'b10;

// Defining a register which stores current and next state
logic [1:0] state;
logic [1:0] next_state;

// State logic (Sequential)
always_ff @(posedge clk or negedge rst_n)
begin
    if (!rst_n)
        state <= IDLE;
    else
        state <= next_state;
end

// Function of the FSM (Combinational)
always_comb begin   
    // To avoid inferred latch (ask Carsten)
    next_state = state;
    reset_cnt_o  = 1'b0;
    pwrup_osc_o   = 1'b0;

    case (state)
        IDLE: begin
            reset_cnt_o = 1'b1; 
            if (start_i) begin
                next_state = CNT;
            end else
                next_state = IDLE;
        end

        CNT: begin
            pwrup_osc_o = 1'b1;
            next_state  = CAPTURE;
        end

        CAPTURE: begin
            next_state  = IDLE;
        end

        default:
            next_state  = IDLE;
    endcase
    
end

// capture counter value and assert complete signal
always_ff @(posedge clk or negedge rst_n) begin
    completed_o <= 1'b0;
    if (!rst_n) begin
        clk_cycles_o <= '0;
        completed_o <= 1'b1;
    end else if (state == CAPTURE) begin
        clk_cycles_o <= cnt_i;
        completed_o <= 1'b1;
    end
end

endmodule

rtl/sensor.v
`timescale 1 ns / 1 ps

module sensor #(
    parameter CNT_WIDTH = 8
)(
    input  logic clk,
    input  logic rst_n,
    input  logic start_i,
    input  logic osc_i,
    output logic completed_o,
    output logic [CNT_WIDTH-1:0] clk_cycles_o
);

logic pwrup_osc;
logic reset_cnt;
logic [CNT_WIDTH-1:0] cnt;

// FSM instance
counter_fsm #(
    .CNT_WIDTH(CNT_WIDTH)
) u_fsm (
    .clk(clk),
    .rst_n(rst_n),
    .start_i(start_i),
    .cnt_i(cnt),
    .pwrup_osc_o(pwrup_osc),
    .reset_cnt_o(reset_cnt),
    .completed_o(completed_o),
    .clk_cycles_o(clk_cycles_o)
);

// Counter instance
counter #(
    .CNT_WIDTH(CNT_WIDTH)
) u_counter (
    .osc_i(osc_i & pwrup_osc), // idea: only count when powered
    //.osc_i(osc_i),
    .reset_cnt_i(reset_cnt),
    .cnt_o(cnt)
);

endmodule

rtl/sensor_tb.v
`timescale 1 ns / 1 ps

module sensor_tb;
    // save data for waveform viewer
    initial begin
        $dumpfile("../sim/LELO_GR02/sensor_tb_sim.vcd");
        $dumpvars(0, sensor_tb);
    end

    parameter CNT_WIDTH = 9;

    // ---------
    // Signal generation
    // ---------
    logic clk;
    logic rst_n;
    logic start;
    logic osc;
    logic completed;
    logic [CNT_WIDTH-1:0] clk_cycles;

    // DUT
    sensor #(.CNT_WIDTH(CNT_WIDTH)) dut (
        .clk(clk),
        .rst_n(rst_n),
        .start_i(start),
        .osc_i(osc),
        .completed_o(completed),
        .clk_cycles_o(clk_cycles)
    );

    // system clock @ 32786 Hz
    real T_sysclk = 30518.0; // period in ns
    initial clk = 0;
    always #($rtoi(T_sysclk/2.0)) clk = ~clk; // make it wobble :)

    // set up lookup table
    // loading from csv does not seem to play nicely with icarus iverilog
    parameter POINTS = 5;
    real temp_table[POINTS-1:0];
    real period_table[POINTS-1:0];

    // lookup table
    initial begin
        temp_table[0] =  0.0;   period_table[0] = 1000.0;
        temp_table[1] =  20.0;  period_table[1] = 500.0;
        temp_table[2] =  40.0;  period_table[2] = 400.0;
        temp_table[3] =  60.0;  period_table[3] = 300.0;
        temp_table[4] =  80.0;  period_table[4] = 100.0;
    end

    // linear interpolation
    function real temp_to_period;
        input real temp;

        integer i;
        real t0, t1, p0, p1;
    begin
        // clamping
        if (temp <= temp_table[0]) temp_to_period = period_table[0];
        else if (temp >= temp_table[POINTS-1]) temp_to_period = period_table[POINTS-1];

        // calc period from temp
        else begin
            for (i = 0; i < POINTS-1; i = i+1) begin
                if ((temp >= temp_table[i]) && (temp <= temp_table[i+1])) begin
                    t0 = temp_table[i];
                    t1 = temp_table[i+1];

                    p0 = period_table[i];
                    p1 = period_table[i+1];

                    temp_to_period = p0 + (p1-p0) * (temp-t0) / (t1-t0);
                end
            end
        end
    end
    endfunction

    // OSC
    real temp;
    real period;
    initial osc = 0;
    always #($rtoi(period/2.0)) osc = ~osc;

    // ----------------
    // actual testbench
    // ----------------
    integer pass_cnt, fail_cnt;
    integer tol;
    integer expected;
    real temp_step;

    // generate start signal whenever completed goes high (asap, same cylce for maximum stresstest)
    logic first_start_done;

    // start is high if it's the first start or completed is high
    assign start = (!first_start_done) ? 1'b1 : completed;

    // kickstart logic for start signal
    always @(posedge clk or negedge rst_n) begin
        if (!rst_n)
            first_start_done <= 0;
        else
            first_start_done <= 1;
    end

    initial begin
        $display("+++ TESTING SENSOR +++");

        // settings
        temp = 0.0;
        tol = 2;
        temp_step = 5.0;
        
        period = temp_to_period(temp);
        rst_n = 0;
        pass_cnt = 0;
        fail_cnt = 0;

        #100us;
        rst_n = 1;

        repeat (20) begin
            period = temp_to_period(temp);

            // wait for FSM completion
            @(posedge completed);

            // calc expected cycles
            expected = T_sysclk / period;

            // check if expected matches relaity (with tolerance)
            if ((clk_cycles >= expected-tol) && (clk_cycles <= expected+tol)) begin
                $display("PASS | Temp=%0.1f | Cnt=%0d | Exp=%0d | Per=%0.1f", temp, clk_cycles, expected, period);
                pass_cnt = pass_cnt + 1;
            end else begin
                $display("FAIL | Temp=%0.1f | Cnt=%0d | Exp=%0d | Per=%0.1f", temp, clk_cycles, expected, period);
                fail_cnt = fail_cnt + 1;
            end

            temp = temp + temp_step;
        end

        $display("\n==============================");
        $display("Tests PASSED: %0d", pass_cnt);
        $display("Tests FAILED: %0d", fail_cnt);
        $display("==============================\n");

        if (fail_cnt == 0) $display("ALL TESTS PASSED");
        else $display("TESTS FAILED");
        $display("+++ TESTING SENSOR DONE +++");

        #100us;
        $finish;
    end
endmodule

sim/LELO_GR02/sensor_tb_sim.vcd
$date
	Sat Mar 21 18:58:21 2026
$end
$version
	Icarus Verilog
$end
$timescale
	1ps
$end
$scope module sensor_tb $end
$var wire 1 ! start $end
$var wire 1 " completed $end
$var wire 9 # clk_cycles [8:0] $end
$var parameter 32 $ CNT_WIDTH $end
$var parameter 32 % POINTS $end
$var reg 1 & clk $end
$var reg 1 ' first_start_done $end
$var reg 1 ( osc $end
$var reg 1 ) rst_n $end
$var real 1 * T_sysclk $end
$var integer 32 + expected [31:0] $end
$var integer 32 , fail_cnt [31:0] $end
$var integer 32 - pass_cnt [31:0] $end
$var real 1 . period $end
$var real 1 / temp $end
$var real 1 0 temp_step $end
$var integer 32 1 tol [31:0] $end
$scope function temp_to_period $end
$var integer 32 2 i [31:0] $end
$var real 1 3 p0 $end
$var real 1 4 p1 $end
$var real 1 5 t0 $end
$var real 1 6 t1 $end
$var real 1 7 temp $end
$upscope $end
$scope module dut $end
$var wire 1 & clk $end
$var wire 1 ( osc_i $end
$var wire 1 ) rst_n $end
$var wire 1 ! start_i $end
$var wire 1 8 reset_cnt $end
$var wire 1 9 pwrup_osc $end
$var wire 1 " completed_o $end
$var wire 9 : cnt [8:0] $end
$var wire 9 ; clk_cycles_o [8:0] $end
$var parameter 32 < CNT_WIDTH $end
$scope module u_counter $end
$var wire 1 = osc_i $end
$var wire 1 8 reset_cnt_i $end
$var parameter 32 > CNT_WIDTH $end
$var reg 9 ? cnt_o [8:0] $end
$upscope $end
$scope module u_fsm $end
$var wire 1 & clk $end
$var wire 9 @ cnt_i [8:0] $end
$var wire 1 ) rst_n $end
$var wire 1 ! start_i $end
$var parameter 2 A CAPTURE $end
$var parameter 2 B CNT $end
$var parameter 32 C CNT_WIDTH $end
$var parameter 2 D IDLE $end
$var reg 9 E clk_cycles_o [8:0] $end
$var reg 1 " completed_o $end
$var reg 2 F next_state [1:0] $end
$var reg 1 9 pwrup_osc_o $end
$var reg 1 8 reset_cnt_o $end
$var reg 2 G state [1:0] $end
$upscope $end
$upscope $end
$upscope $end
$enddefinitions $end
$comment Show the parameter values. $end
$dumpall
b0 D
b1001 C
b1 B
b10 A
b1001 >
b1001 <
b101 %
b1001 $
$end
#0
$dumpvars
b0 G
b1 F
b0 E
b0 @
b0 ?
0=
b0 ;
b0 :
09
18
r0 7
r0 6
r0 5
r0 4
r0 3
bx 2
b10 1
r5 0
r0 /
r1000 .
b0 -
b0 ,
bx +
r30518 *
0)
1(
0'
0&
b0 #
0"
1!
$end
#500000
0(
#1000000
1(
#1500000
0(
#2000000
1(
#2500000
0(
#3000000
1(
#3500000
0(
#4000000
1(
#4500000
0(
#5000000
1(
#5500000
0(
#6000000
1(
#6500000
0(
#7000000
1(
#7500000
0(
#8000000
1(
#8500000
0(
#9000000
1(
#9500000
0(
#10000000
1(
#10500000
0(
#11000000
1(
#11500000
0(
#12000000
1(
#12500000
0(
#13000000
1(
#13500000
0(
#14000000
1(
#14500000
0(
#15000000
1(
#15259000
1&
#15500000
0(
#16000000
1(
#16500000
0(
#17000000
1(
#17500000
0(
#18000000
1(
#18500000
0(
#19000000
1(
#19500000
0(
#20000000
1(
#20500000
0(
#21000000
1(
#21500000
0(
#22000000
1(
#22500000
0(
#23000000
1(
#23500000
0(
#24000000
1(
#24500000
0(
#25000000
1(
#25500000
0(
#26000000
1(
#26500000
0(
#27000000
1(
#27500000
0(
#28000000
1(
#28500000
0(
#29000000
1(
#29500000
0(
#30000000
1(
#30500000
0(
#30518000
0&
#31000000
1(
#31500000
0(
#32000000
1(
#32500000
0(
#33000000
1(
#33500000
0(
#34000000
1(
#34500000
0(
#35000000
1(
#35500000
0(
#36000000
1(
#36500000
0(
#37000000
1(
#37500000
0(
#38000000
1(
#38500000
0(
#39000000
1(
#39500000
0(
#40000000
1(
#40500000
0(
#41000000
1(
#41500000
0(
#42000000
1(
#42500000
0(
#43000000
1(
#43500000
0(
#44000000
1(
#44500000
0(
#45000000
1(
#45500000
0(
#45777000
1&
#46000000
1(
#46500000
0(
#47000000
1(
#47500000
0(
#48000000
1(
#48500000
0(
#49000000
1(
#49500000
0(
#50000000
1(
#50500000
0(
#51000000
1(
#51500000
0(
#52000000
1(
#52500000
0(
#53000000
1(
#53500000
0(
#54000000
1(
#54500000
0(
#55000000
1(
#55500000
0(
#56000000
1(
#56500000
0(
#57000000
1(
#57500000
0(
#58000000
1(
#58500000
0(
#59000000
1(
#59500000
0(
#60000000
1(
#60500000
0(
#61000000
1(
#61036000
0&
#61500000
0(
#62000000
1(
#62500000
0(
#63000000
1(
#63500000
0(
#64000000
1(
#64500000
0(
#65000000
1(
#65500000
0(
#66000000
1(
#66500000
0(
#67000000
1(
#67500000
0(
#68000000
1(
#68500000
0(
#69000000
1(
#69500000
0(
#70000000
1(
#70500000
0(
#71000000
1(
#71500000
0(
#72000000
1(
#72500000
0(
#73000000
1(
#73500000
0(
#74000000
1(
#74500000
0(
#75000000
1(
#75500000
0(
#76000000
1(
#76295000
1&
#76500000
0(
#77000000
1(
#77500000
0(
#78000000
1(
#78500000
0(
#79000000
1(
#79500000
0(
#80000000
1(
#80500000
0(
#81000000
1(
#81500000
0(
#82000000
1(
#82500000
0(
#83000000
1(
#83500000
0(
#84000000
1(
#84500000
0(
#85000000
1(
#85500000
0(
#86000000
1(
#86500000
0(
#87000000
1(
#87500000
0(
#88000000
1(
#88500000
0(
#89000000
1(
#89500000
0(
#90000000
1(
#90500000
0(
#91000000
1(
#91500000
0(
#91554000
0&
#92000000
1(
#92500000
0(
#93000000
1(
#93500000
0(
#94000000
1(
#94500000
0(
#95000000
1(
#95500000
0(
#96000000
1(
#96500000
0(
#97000000
1(
#97500000
0(
#98000000
1(
#98500000
0(
#99000000
1(
#99500000
0(
#100000000
1(
1)
#100500000
0(
#101000000
1(
#101500000
0(
#102000000
1(
#102500000
0(
#103000000
1(
#103500000
0(
#104000000
1(
#104500000
0(
#105000000
1(
#105500000
0(
#106000000
1(
#106500000
0(
#106813000
b10 F
19
08
0!
b1 G
1'
1&
#107000000
b1 :
b1 ?
b1 @
1=
1(
#107500000
0=
0(
#108000000
b10 :
b10 ?
b10 @
1=
1(
#108500000
0=
0(
#109000000
b11 :
b11 ?
b11 @
1=
1(
#109500000
0=
0(
#110000000
b100 :
b100 ?
b100 @
1=
1(
#110500000
0=
0(
#111000000
b101 :
b101 ?
b101 @
1=
1(
#111500000
0=
0(
#112000000
b110 :
b110 ?
b110 @
1=
1(
#112500000
0=
0(
#113000000
b111 :
b111 ?
b111 @
1=
1(
#113500000
0=
0(
#114000000
b1000 :
b1000 ?
b1000 @
1=
1(
#114500000
0=
0(
#115000000
b1001 :
b1001 ?
b1001 @
1=
1(
#115500000
0=
0(
#116000000
b1010 :
b1010 ?
b1010 @
1=
1(
#116500000
0=
0(
#117000000
b1011 :
b1011 ?
b1011 @
1=
1(
#117500000
0=
0(
#118000000
b1100 :
b1100 ?
b1100 @
1=
1(
#118500000
0=
0(
#119000000
b1101 :
b1101 ?
b1101 @
1=
1(
#119500000
0=
0(
#120000000
b1110 :
b1110 ?
b1110 @
1=
1(
#120500000
0=
0(
#121000000
b1111 :
b1111 ?
b1111 @
1=
1(
#121500000
0=
0(
#122000000
b10000 :
b10000 ?
b10000 @
1=
1(
#122072000
0&
#122500000
0=
0(
#123000000
b10001 :
b10001 ?
b10001 @
1=
1(
#123500000
0=
0(
#124000000
b10010 :
b10010 ?
b10010 @
1=
1(
#124500000
0=
0(
#125000000
b10011 :
b10011 ?
b10011 @
1=
1(
#125500000
0=
0(
#126000000
b10100 :
b10100 ?
b10100 @
1=
1(
#126500000
0=
0(
#127000000
b10101 :
b10101 ?
b10101 @
1=
1(
#127500000
0=
0(
#128000000
b10110 :
b10110 ?
b10110 @
1=
1(
#128500000
0=
0(
#129000000
b10111 :
b10111 ?
b10111 @
1=
1(
#129500000
0=
0(
#130000000
b11000 :
b11000 ?
b11000 @
1=
1(
#130500000
0=
0(
#131000000
b11001 :
b11001 ?
b11001 @
1=
1(
#131500000
0=
0(
#132000000
b11010 :
b11010 ?
b11010 @
1=
1(
#132500000
0=
0(
#133000000
b11011 :
b11011 ?
b11011 @
1=
1(
#133500000
0=
0(
#134000000
b11100 :
b11100 ?
b11100 @
1=
1(
#134500000
0=
0(
#135000000
b11101 :
b11101 ?
b11101 @
1=
1(
#135500000
0=
0(
#136000000
b11110 :
b11110 ?
b11110 @
1=
1(
#136500000
0=
0(
#137000000
b11111 :
b11111 ?
b11111 @
1=
1(
#137331000
0=
b0 F
09
b10 G
1&
#137500000
0(
#138000000
1(
#138500000
0(
#139000000
1(
#139500000
0(
#140000000
1(
#140500000
0(
#141000000
1(
#141500000
0(
#142000000
1(
#142500000
0(
#143000000
1(
#143500000
0(
#144000000
1(
#144500000
0(
#145000000
1(
#145500000
0(
#146000000
1(
#146500000
0(
#147000000
1(
#147500000
0(
#148000000
1(
#148500000
0(
#149000000
1(
#149500000
0(
#150000000
1(
#150500000
0(
#151000000
1(
#151500000
0(
#152000000
1(
#152500000
0(
#152590000
0&
#153000000
1(
#153500000
0(
#154000000
1(
#154500000
0(
#155000000
1(
#155500000
0(
#156000000
1(
#156500000
0(
#157000000
1(
#157500000
0(
#158000000
1(
#158500000
0(
#159000000
1(
#159500000
0(
#160000000
1(
#160500000
0(
#161000000
1(
#161500000
0(
#162000000
1(
#162500000
0(
#163000000
1(
#163500000
0(
#164000000
1(
#164500000
0(
#165000000
1(
#165500000
0(
#166000000
1(
#166500000
0(
#167000000
1(
#167500000
0(
#167849000
b0 :
b0 ?
b0 @
b1 F
18
1!
r875 .
r500 4
r1000 3
r20 6
b100 2
r5 7
r5 /
b1 -
b11111 +
b0 G
1"
b11111 #
b11111 ;
b11111 E
1&
#168000000
1(
#168437000
0(
#168874000
1(
#169311000
0(
#169748000
1(
#170185000
0(
#170622000
1(
#171059000
0(
#171496000
1(
#171933000
0(
#172370000
1(
#172807000
0(
#173244000
1(
#173681000
0(
#174118000
1(
#174555000
0(
#174992000
1(
#175429000
0(
#175866000
1(
#176303000
0(
#176740000
1(
#177177000
0(
#177614000
1(
#178051000
0(
#178488000
1(
#178925000
0(
#179362000
1(
#179799000
0(
#180236000
1(
#180673000
0(
#181110000
1(
#181547000
0(
#181984000
1(
#182421000
0(
#182858000
1(
#183108000
0&
#183295000
0(
#183732000
1(
#184169000
0(
#184606000
1(
#185043000
0(
#185480000
1(
#185917000
0(
#186354000
1(
#186791000
0(
#187228000
1(
#187665000
0(
#188102000
1(
#188539000
0(
#188976000
1(
#189413000
0(
#189850000
1(
#190287000
0(
#190724000
1(
#191161000
0(
#191598000
1(
#192035000
0(
#192472000
1(
#192909000
0(
#193346000
1(
#193783000
0(
#194220000
1(
#194657000
0(
#195094000
1(
#195531000
0(
#195968000
1(
#196405000
0(
#196842000
1(
#197279000
0(
#197716000
1(
#198153000
0(
#198367000
0!
b10 F
19
08
0"
b1 G
1&
#198590000
b1 :
b1 ?
b1 @
1=
1(
#199027000
0=
0(
#199464000
b10 :
b10 ?
b10 @
1=
1(
#199901000
0=
0(
#200338000
b11 :
b11 ?
b11 @
1=
1(
#200775000
0=
0(
#201212000
b100 :
b100 ?
b100 @
1=
1(
#201649000
0=
0(
#202086000
b101 :
b101 ?
b101 @
1=
1(
#202523000
0=
0(
#202960000
b110 :
b110 ?
b110 @
1=
1(
#203397000
0=
0(
#203834000
b111 :
b111 ?
b111 @
1=
1(
#204271000
0=
0(
#204708000
b1000 :
b1000 ?
b1000 @
1=
1(
#205145000
0=
0(
#205582000
b1001 :
b1001 ?
b1001 @
1=
1(
#206019000
0=
0(
#206456000
b1010 :
b1010 ?
b1010 @
1=
1(
#206893000
0=
0(
#207330000
b1011 :
b1011 ?
b1011 @
1=
1(
#207767000
0=
0(
#208204000
b1100 :
b1100 ?
b1100 @
1=
1(
#208641000
0=
0(
#209078000
b1101 :
b1101 ?
b1101 @
1=
1(
#209515000
0=
0(
#209952000
b1110 :
b1110 ?
b1110 @
1=
1(
#210389000
0=
0(
#210826000
b1111 :
b1111 ?
b1111 @
1=
1(
#211263000
0=
0(
#211700000
b10000 :
b10000 ?
b10000 @
1=
1(
#212137000
0=
0(
#212574000
b10001 :
b10001 ?
b10001 @
1=
1(
#213011000
0=
0(
#213448000
b10010 :
b10010 ?
b10010 @
1=
1(
#213626000
0&
#213885000
0=
0(
#214322000
b10011 :
b10011 ?
b10011 @
1=
1(
#214759000
0=
0(
#215196000
b10100 :
b10100 ?
b10100 @
1=
1(
#215633000
0=
0(
#216070000
b10101 :
b10101 ?
b10101 @
1=
1(
#216507000
0=
0(
#216944000
b10110 :
b10110 ?
b10110 @
1=
1(
#217381000
0=
0(
#217818000
b10111 :
b10111 ?
b10111 @
1=
1(
#218255000
0=
0(
#218692000
b11000 :
b11000 ?
b11000 @
1=
1(
#219129000
0=
0(
#219566000
b11001 :
b11001 ?
b11001 @
1=
1(
#220003000
0=
0(
#220440000
b11010 :
b11010 ?
b11010 @
1=
1(
#220877000
0=
0(
#221314000
b11011 :
b11011 ?
b11011 @
1=
1(
#221751000
0=
0(
#222188000
b11100 :
b11100 ?
b11100 @
1=
1(
#222625000
0=
0(
#223062000
b11101 :
b11101 ?
b11101 @
1=
1(
#223499000
0=
0(
#223936000
b11110 :
b11110 ?
b11110 @
1=
1(
#224373000
0=
0(
#224810000
b11111 :
b11111 ?
b11111 @
1=
1(
#225247000
0=
0(
#225684000
b100000 :
b100000 ?
b100000 @
1=
1(
#226121000
0=
0(
#226558000
b100001 :
b100001 ?
b100001 @
1=
1(
#226995000
0=
0(
#227432000
b100010 :
b100010 ?
b100010 @
1=
1(
#227869000
0=
0(
#228306000
b100011 :
b100011 ?
b100011 @
1=
1(
#228743000
0=
0(
#228885000
b0 F
09
b10 G
1&
#229180000
1(
#229617000
0(
#230054000
1(
#230491000
0(
#230928000
1(
#231365000
0(
#231802000
1(
#232239000
0(
#232676000
1(
#233113000
0(
#233550000
1(
#233987000
0(
#234424000
1(
#234861000
0(
#235298000
1(
#235735000
0(
#236172000
1(
#236609000
0(
#237046000
1(
#237483000
0(
#237920000
1(
#238357000
0(
#238794000
1(
#239231000
0(
#239668000
1(
#240105000
0(
#240542000
1(
#240979000
0(
#241416000
1(
#241853000
0(
#242290000
1(
#242727000
0(
#243164000
1(
#243601000
0(
#244038000
1(
#244144000
0&
#244475000
0(
#244912000
1(
#245349000
0(
#245786000
1(
#246223000
0(
#246660000
1(
#247097000
0(
#247534000
1(
#247971000
0(
#248408000
1(
#248845000
0(
#249282000
1(
#249719000
0(
#250156000
1(
#250593000
0(
#251030000
1(
#251467000
0(
#251904000
1(
#252341000
0(
#252778000
1(
#253215000
0(
#253652000
1(
#254089000
0(
#254526000
1(
#254963000
0(
#255400000
1(
#255837000
0(
#256274000
1(
#256711000
0(
#257148000
1(
#257585000
0(
#258022000
1(
#258459000
0(
#258896000
1(
#259333000
0(
#259403000
b0 :
b0 ?
b0 @
b1 F
1!
r750 .
b100 2
r10 7
r10 /
b10 -
b100011 +
18
b100011 #
b100011 ;
b100011 E
1"
b0 G
1&
#259770000
1(
#260145000
0(
#260520000
1(
#260895000
0(
#261270000
1(
#261645000
0(
#262020000
1(
#262395000
0(
#262770000
1(
#263145000
0(
#263520000
1(
#263895000
0(
#264270000
1(
#264645000
0(
#265020000
1(
#265395000
0(
#265770000
1(
#266145000
0(
#266520000
1(
#266895000
0(
#267270000
1(
#267645000
0(
#268020000
1(
#268395000
0(
#268770000
1(
#269145000
0(
#269520000
1(
#269895000
0(
#270270000
1(
#270645000
0(
#271020000
1(
#271395000
0(
#271770000
1(
#272145000
0(
#272520000
1(
#272895000
0(
#273270000
1(
#273645000
0(
#274020000
1(
#274395000
0(
#274662000
0&
#274770000
1(
#275145000
0(
#275520000
1(
#275895000
0(
#276270000
1(
#276645000
0(
#277020000
1(
#277395000
0(
#277770000
1(
#278145000
0(
#278520000
1(
#278895000
0(
#279270000
1(
#279645000
0(
#280020000
1(
#280395000
0(
#280770000
1(
#281145000
0(
#281520000
1(
#281895000
0(
#282270000
1(
#282645000
0(
#283020000
1(
#283395000
0(
#283770000
1(
#284145000
0(
#284520000
1(
#284895000
0(
#285270000
1(
#285645000
0(
#286020000
1(
#286395000
0(
#286770000
1(
#287145000
0(
#287520000
1(
#287895000
0(
#288270000
1(
#288645000
0(
#289020000
1(
#289395000
0(
#289770000
1(
#289921000
b1 :
b1 ?
b1 @
1=
b10 F
19
08
0!
b1 G
0"
1&
#290145000
0=
0(
#290520000
b10 :
b10 ?
b10 @
1=
1(
#290895000
0=
0(
#291270000
b11 :
b11 ?
b11 @
1=
1(
#291645000
0=
0(
#292020000
b100 :
b100 ?
b100 @
1=
1(
#292395000
0=
0(
#292770000
b101 :
b101 ?
b101 @
1=
1(
#293145000
0=
0(
#293520000
b110 :
b110 ?
b110 @
1=
1(
#293895000
0=
0(
#294270000
b111 :
b111 ?
b111 @
1=
1(
#294645000
0=
0(
#295020000
b1000 :
b1000 ?
b1000 @
1=
1(
#295395000
0=
0(
#295770000
b1001 :
b1001 ?
b1001 @
1=
1(
#296145000
0=
0(
#296520000
b1010 :
b1010 ?
b1010 @
1=
1(
#296895000
0=
0(
#297270000
b1011 :
b1011 ?
b1011 @
1=
1(
#297645000
0=
0(
#298020000
b1100 :
b1100 ?
b1100 @
1=
1(
#298395000
0=
0(
#298770000
b1101 :
b1101 ?
b1101 @
1=
1(
#299145000
0=
0(
#299520000
b1110 :
b1110 ?
b1110 @
1=
1(
#299895000
0=
0(
#300270000
b1111 :
b1111 ?
b1111 @
1=
1(
#300645000
0=
0(
#301020000
b10000 :
b10000 ?
b10000 @
1=
1(
#301395000
0=
0(
#301770000
b10001 :
b10001 ?
b10001 @
1=
1(
#302145000
0=
0(
#302520000
b10010 :
b10010 ?
b10010 @
1=
1(
#302895000
0=
0(
#303270000
b10011 :
b10011 ?
b10011 @
1=
1(
#303645000
0=
0(
#304020000
b10100 :
b10100 ?
b10100 @
1=
1(
#304395000
0=
0(
#304770000
b10101 :
b10101 ?
b10101 @
1=
1(
#305145000
0=
0(
#305180000
0&
#305520000
b10110 :
b10110 ?
b10110 @
1=
1(
#305895000
0=
0(
#306270000
b10111 :
b10111 ?
b10111 @
1=
1(
#306645000
0=
0(
#307020000
b11000 :
b11000 ?
b11000 @
1=
1(
#307395000
0=
0(
#307770000
b11001 :
b11001 ?
b11001 @
1=
1(
#308145000
0=
0(
#308520000
b11010 :
b11010 ?
b11010 @
1=
1(
#308895000
0=
0(
#309270000
b11011 :
b11011 ?
b11011 @
1=
1(
#309645000
0=
0(
#310020000
b11100 :
b11100 ?
b11100 @
1=
1(
#310395000
0=
0(
#310770000
b11101 :
b11101 ?
b11101 @
1=
1(
#311145000
0=
0(
#311520000
b11110 :
b11110 ?
b11110 @
1=
1(
#311895000
0=
0(
#312270000
b11111 :
b11111 ?
b11111 @
1=
1(
#312645000
0=
0(
#313020000
b100000 :
b100000 ?
b100000 @
1=
1(
#313395000
0=
0(
#313770000
b100001 :
b100001 ?
b100001 @
1=
1(
#314145000
0=
0(
#314520000
b100010 :
b100010 ?
b100010 @
1=
1(
#314895000
0=
0(
#315270000
b100011 :
b100011 ?
b100011 @
1=
1(
#315645000
0=
0(
#316020000
b100100 :
b100100 ?
b100100 @
1=
1(
#316395000
0=
0(
#316770000
b100101 :
b100101 ?
b100101 @
1=
1(
#317145000
0=
0(
#317520000
b100110 :
b100110 ?
b100110 @
1=
1(
#317895000
0=
0(
#318270000
b100111 :
b100111 ?
b100111 @
1=
1(
#318645000
0=
0(
#319020000
b101000 :
b101000 ?
b101000 @
1=
1(
#319395000
0=
0(
#319770000
b101001 :
b101001 ?
b101001 @
1=
1(
#320145000
0=
0(
#320439000
b0 F
09
b10 G
1&
#320520000
1(
#320895000
0(
#321270000
1(
#321645000
0(
#322020000
1(
#322395000
0(
#322770000
1(
#323145000
0(
#323520000
1(
#323895000
0(
#324270000
1(
#324645000
0(
#325020000
1(
#325395000
0(
#325770000
1(
#326145000
0(
#326520000
1(
#326895000
0(
#327270000
1(
#327645000
0(
#328020000
1(
#328395000
0(
#328770000
1(
#329145000
0(
#329520000
1(
#329895000
0(
#330270000
1(
#330645000
0(
#331020000
1(
#331395000
0(
#331770000
1(
#332145000
0(
#332520000
1(
#332895000
0(
#333270000
1(
#333645000
0(
#334020000
1(
#334395000
0(
#334770000
1(
#335145000
0(
#335520000
1(
#335698000
0&
#335895000
0(
#336270000
1(
#336645000
0(
#337020000
1(
#337395000
0(
#337770000
1(
#338145000
0(
#338520000
1(
#338895000
0(
#339270000
1(
#339645000
0(
#340020000
1(
#340395000
0(
#340770000
1(
#341145000
0(
#341520000
1(
#341895000
0(
#342270000
1(
#342645000
0(
#343020000
1(
#343395000
0(
#343770000
1(
#344145000
0(
#344520000
1(
#344895000
0(
#345270000
1(
#345645000
0(
#346020000
1(
#346395000
0(
#346770000
1(
#347145000
0(
#347520000
1(
#347895000
0(
#348270000
1(
#348645000
0(
#349020000
1(
#349395000
0(
#349770000
1(
#350145000
0(
#350520000
1(
#350895000
0(
#350957000
b0 :
b0 ?
b0 @
b1 F
18
1!
r625 .
b100 2
r15 7
r15 /
b11 -
b101001 +
b0 G
1"
b101001 #
b101001 ;
b101001 E
1&
#351270000
1(
#351582000
0(
#351894000
1(
#352206000
0(
#352518000
1(
#352830000
0(
#353142000
1(
#353454000
0(
#353766000
1(
#354078000
0(
#354390000
1(
#354702000
0(
#355014000
1(
#355326000
0(
#355638000
1(
#355950000
0(
#356262000
1(
#356574000
0(
#356886000
1(
#357198000
0(
#357510000
1(
#357822000
0(
#358134000
1(
#358446000
0(
#358758000
1(
#359070000
0(
#359382000
1(
#359694000
0(
#360006000
1(
#360318000
0(
#360630000
1(
#360942000
0(
#361254000
1(
#361566000
0(
#361878000
1(
#362190000
0(
#362502000
1(
#362814000
0(
#363126000
1(
#363438000
0(
#363750000
1(
#364062000
0(
#364374000
1(
#364686000
0(
#364998000
1(
#365310000
0(
#365622000
1(
#365934000
0(
#366216000
0&
#366246000
1(
#366558000
0(
#366870000
1(
#367182000
0(
#367494000
1(
#367806000
0(
#368118000
1(
#368430000
0(
#368742000
1(
#369054000
0(
#369366000
1(
#369678000
0(
#369990000
1(
#370302000
0(
#370614000
1(
#370926000
0(
#371238000
1(
#371550000
0(
#371862000
1(
#372174000
0(
#372486000
1(
#372798000
0(
#373110000
1(
#373422000
0(
#373734000
1(
#374046000
0(
#374358000
1(
#374670000
0(
#374982000
1(
#375294000
0(
#375606000
1(
#375918000
0(
#376230000
1(
#376542000
0(
#376854000
1(
#377166000
0(
#377478000
1(
#377790000
0(
#378102000
1(
#378414000
0(
#378726000
1(
#379038000
0(
#379350000
1(
#379662000
0(
#379974000
1(
#380286000
0(
#380598000
1(
#380910000
0(
#381222000
1(
#381475000
b1 :
b1 ?
b1 @
1=
0!
b10 F
19
08
0"
b1 G
1&
#381534000
0=
0(
#381846000
b10 :
b10 ?
b10 @
1=
1(
#382158000
0=
0(
#382470000
b11 :
b11 ?
b11 @
1=
1(
#382782000
0=
0(
