rtl/counter.v
`timescale 1 ns / 1 ps

module counter #(
    parameter CNT_WIDTH = 8
)(
    input  logic osc_i,
    input  logic reset_cnt_i,
    output logic [CNT_WIDTH-1:0] cnt_o
);

always_ff @(posedge osc_i or posedge reset_cnt_i) begin
    if (reset_cnt_i)
        cnt_o <= '0;
    else if (cnt_o != {CNT_WIDTH{1'b1}}) // clamp at max value
        cnt_o <= cnt_o + 1;
end

endmodule

rtl/fsm.v
`timescale 1 ns / 1 ps

module counter_fsm #(
    parameter CNT_WIDTH = 8
)(
    input logic clk,
    input logic rst_n,
    input logic start_i,
    input logic [CNT_WIDTH-1:0] cnt_i,
    output logic pwrup_osc_o,
    output logic reset_cnt_o, 
    output logic completed_o,  
    output logic [CNT_WIDTH-1:0] clk_cycles_o
);

// Assigning state names to binary values
parameter IDLE    = 2'b00;
parameter PWRUP   = 2'b01;
parameter PWRDWN  = 2'b10;
parameter CAPTURE = 2'b11;

// Defining a register which stores current and next state
logic [1:0] state;
logic [1:0] next_state;

// State logic (Sequential)
always_ff @(posedge clk or negedge rst_n)
begin
    if (!rst_n)
        state <= IDLE;
    else
        state <= next_state;
end

// Function of the FSM (Combinational)
always_comb begin   

    // To avoid inferred latch (ask Carsten)
    next_state = state;
    reset_cnt_o  = 1'b0;
    pwrup_osc_o   = 1'b0;
    completed_o  = 1'b0;

    case (state)

        IDLE: begin
            reset_cnt_o = 1'b1; 
            if (start_i)
                next_state = PWRUP;
            else
                next_state = IDLE;
        end

        PWRUP: begin
            pwrup_osc_o = 1'b1;
            next_state  = PWRDWN;
        end

        PWRDWN: begin
            next_state  = CAPTURE;
        end

        CAPTURE: begin
            completed_o   = 1'b1;
            next_state  = IDLE;
        end

    endcase
    
end

// Data Capture (Sequential)
always_ff @(posedge clk or negedge rst_n) begin
    if (!rst_n)
        clk_cycles_o <= '0;
    else if (state == PWRDWN)
        clk_cycles_o <= cnt_i;
end

endmodule

rtl/sensor.v
`timescale 1 ns / 1 ps

module sensor #(
    parameter CNT_WIDTH = 8
)(
    input  logic clk,
    input  logic rst_n,
    input  logic start_i,
    input  logic osc_i,
    output logic completed_o,
    output logic [CNT_WIDTH-1:0] clk_cycles_o
);

logic pwrup_osc;
logic reset_cnt;
logic [CNT_WIDTH-1:0] cnt;

// FSM instance
counter_fsm #(
    .CNT_WIDTH(CNT_WIDTH)
) u_fsm (
    .clk(clk),
    .rst_n(rst_n),
    .start_i(start_i),
    .cnt_i(cnt),
    .pwrup_osc_o(pwrup_osc),
    .reset_cnt_o(reset_cnt),
    .completed_o(completed_o),
    .clk_cycles_o(clk_cycles_o)
);

// Counter instance
counter #(
    .CNT_WIDTH(CNT_WIDTH)
) u_counter (
    .osc_i(osc_i & pwrup_osc), // idea: only count when powered
    //.osc_i(osc_i),
    .reset_cnt_i(reset_cnt),
    .cnt_o(cnt)
);

endmodule

rtl/sensor_tb.v
`timescale 1 ns / 1 ps

module sensor_tb;
    // save data for waveform viewer
    initial begin
        $dumpfile("../sim/LELO_GR02/sensor_tb_sim.vcd");
        $dumpvars(0, sensor_tb);
    end

    parameter CNT_WIDTH = 9;

    // ---------
    // Signal generation
    // ---------
    logic clk;
    logic rst_n;
    logic start;
    logic osc;
    logic completed;
    logic [CNT_WIDTH-1:0] clk_cycles;

    // DUT
    sensor #(.CNT_WIDTH(CNT_WIDTH)) dut (
        .clk(clk),
        .rst_n(rst_n),
        .start_i(start),
        .osc_i(osc),
        .completed_o(completed),
        .clk_cycles_o(clk_cycles)
    );

    // system clock @ 32786 Hz
    real T_sysclk = 30518.0; // period in ns
    initial clk = 0;
    always #($rtoi(T_sysclk/2.0)) clk = ~clk; // make it wobble :)

    // set up lookup table
    // loading from csv does not seem to play nicely with icarus iverilog
    parameter POINTS = 5;
    real temp_table[POINTS-1:0];
    real period_table[POINTS-1:0];

    // lookup table
    initial begin
        temp_table[0] =  0.0;   period_table[0] = 1000.0;
        temp_table[1] =  20.0;  period_table[1] = 500.0;
        temp_table[2] =  40.0;  period_table[2] = 400.0;
        temp_table[3] =  60.0;  period_table[3] = 300.0;
        temp_table[4] =  80.0;  period_table[4] = 100.0;
    end

    // linear interpolation
    function real temp_to_period;
        input real temp;

        integer i;
        real t0, t1, p0, p1;
    begin
        // clamping
        if (temp <= temp_table[0]) temp_to_period = period_table[0];
        else if (temp >= temp_table[POINTS-1]) temp_to_period = period_table[POINTS-1];

        // calc period from temp
        else begin
            for (i = 0; i < POINTS-1; i = i+1) begin
                if ((temp >= temp_table[i]) && (temp <= temp_table[i+1])) begin
                    t0 = temp_table[i];
                    t1 = temp_table[i+1];

                    p0 = period_table[i];
                    p1 = period_table[i+1];

                    temp_to_period = p0 + (p1-p0) * (temp-t0) / (t1-t0);
                end
            end
        end
    end
    endfunction

    // OSC
    real temp;
    real period;
    initial osc = 0;
    always #($rtoi(period/2.0)) osc = ~osc;

    // ----------------
    // actual testbench
    // ----------------
    integer pass_cnt, fail_cnt;
    integer tol;
    integer expected;
    real temp_step;

    initial begin
        $display("+++ TESTING SENSOR +++");

        rst_n = 0;
        start = 0;

        // settings
        temp = 0.0;
        tol = 2;
        temp_step = 5.0;
        
        period = temp_to_period(temp);

        pass_cnt = 0;
        fail_cnt = 0;

        #100us;
        rst_n = 1;

        repeat (20) begin
            #100us;

            period = temp_to_period(temp);

            // start and stop measurement
            @(posedge clk); start = 1;
            @(posedge clk); start = 0;

            // wait for FSM completion
            @(posedge completed);

            // calc expected cycles
            expected = T_sysclk / period;

            // check if expected matches relaity (with tolerance)
            if ((clk_cycles >= expected-tol) && (clk_cycles <= expected+tol)) begin
                $display("PASS | Temp=%0.1f | Cnt=%0d | Exp=%0d | Per=%0.1f", temp, clk_cycles, expected, period);
                pass_cnt = pass_cnt + 1;
            end else begin
                $display("FAIL | Temp=%0.1f | Cnt=%0d | Exp=%0d | Per=%0.1f", temp, clk_cycles, expected, period);
                fail_cnt = fail_cnt + 1;
            end

            temp = temp + temp_step;
        end

        $display("\n==============================");
        $display("Tests PASSED: %0d", pass_cnt);
        $display("Tests FAILED: %0d", fail_cnt);
        $display("==============================\n");

        if (fail_cnt == 0) $display("ALL TESTS PASSED");
        else $display("TESTS FAILED");
        $display("+++ TESTING SENSOR DONE +++");

        #100us;
        $finish;
    end
endmodule

sim/LELO_GR02/sensor_tb_sim.vcd
$date
	Sat Mar 21 18:04:42 2026
$end
$version
	Icarus Verilog
$end
$timescale
	1ps
$end
$scope module sensor_tb $end
$var wire 1 ! completed $end
$var wire 9 " clk_cycles [8:0] $end
$var parameter 32 # CNT_WIDTH $end
$var parameter 32 $ POINTS $end
$var reg 1 % clk $end
$var reg 1 & osc $end
$var reg 1 ' rst_n $end
$var reg 1 ( start $end
$var real 1 ) T_sysclk $end
$var integer 32 * expected [31:0] $end
$var integer 32 + fail_cnt [31:0] $end
$var integer 32 , pass_cnt [31:0] $end
$var real 1 - period $end
$var real 1 . temp $end
$var real 1 / temp_step $end
$var integer 32 0 tol [31:0] $end
$scope function temp_to_period $end
$var integer 32 1 i [31:0] $end
$var real 1 2 p0 $end
$var real 1 3 p1 $end
$var real 1 4 t0 $end
$var real 1 5 t1 $end
$var real 1 6 temp $end
$upscope $end
$scope module dut $end
$var wire 1 % clk $end
$var wire 1 & osc_i $end
$var wire 1 ' rst_n $end
$var wire 1 ( start_i $end
$var wire 1 7 reset_cnt $end
$var wire 1 8 pwrup_osc $end
$var wire 1 ! completed_o $end
$var wire 9 9 cnt [8:0] $end
$var wire 9 : clk_cycles_o [8:0] $end
$var parameter 32 ; CNT_WIDTH $end
$scope module u_counter $end
$var wire 1 < osc_i $end
$var wire 1 7 reset_cnt_i $end
$var parameter 32 = CNT_WIDTH $end
$var reg 9 > cnt_o [8:0] $end
$upscope $end
$scope module u_fsm $end
$var wire 1 % clk $end
$var wire 9 ? cnt_i [8:0] $end
$var wire 1 ' rst_n $end
$var wire 1 ( start_i $end
$var parameter 2 @ CAPTURE $end
$var parameter 32 A CNT_WIDTH $end
$var parameter 2 B IDLE $end
$var parameter 2 C PWRDWN $end
$var parameter 2 D PWRUP $end
$var reg 9 E clk_cycles_o [8:0] $end
$var reg 1 ! completed_o $end
$var reg 2 F next_state [1:0] $end
$var reg 1 8 pwrup_osc_o $end
$var reg 1 7 reset_cnt_o $end
$var reg 2 G state [1:0] $end
$upscope $end
$upscope $end
$upscope $end
$enddefinitions $end
$comment Show the parameter values. $end
$dumpall
b1 D
b10 C
b0 B
b1001 A
b11 @
b1001 =
b1001 ;
b101 $
b1001 #
$end
#0
$dumpvars
b0 G
b0 F
b0 E
b0 ?
b0 >
0<
b0 :
b0 9
08
17
r0 6
r0 5
r0 4
r0 3
r0 2
bx 1
b10 0
r5 /
r0 .
r1000 -
b0 ,
b0 +
bx *
r30518 )
0(
0'
1&
0%
b0 "
0!
$end
#500000
0&
#1000000
1&
#1500000
0&
#2000000
1&
#2500000
0&
#3000000
1&
#3500000
0&
#4000000
1&
#4500000
0&
#5000000
1&
#5500000
0&
#6000000
1&
#6500000
0&
#7000000
1&
#7500000
0&
#8000000
1&
#8500000
0&
#9000000
1&
#9500000
0&
#10000000
1&
#10500000
0&
#11000000
1&
#11500000
0&
#12000000
1&
#12500000
0&
#13000000
1&
#13500000
0&
#14000000
1&
#14500000
0&
#15000000
1&
#15259000
1%
#15500000
0&
#16000000
1&
#16500000
0&
#17000000
1&
#17500000
0&
#18000000
1&
#18500000
0&
#19000000
1&
#19500000
0&
#20000000
1&
#20500000
0&
#21000000
1&
#21500000
0&
#22000000
1&
#22500000
0&
#23000000
1&
#23500000
0&
#24000000
1&
#24500000
0&
#25000000
1&
#25500000
0&
#26000000
1&
#26500000
0&
#27000000
1&
#27500000
0&
#28000000
1&
#28500000
0&
#29000000
1&
#29500000
0&
#30000000
1&
#30500000
0&
#30518000
0%
#31000000
1&
#31500000
0&
#32000000
1&
#32500000
0&
#33000000
1&
#33500000
0&
#34000000
1&
#34500000
0&
#35000000
1&
#35500000
0&
#36000000
1&
#36500000
0&
#37000000
1&
#37500000
0&
#38000000
1&
#38500000
0&
#39000000
1&
#39500000
0&
#40000000
1&
#40500000
0&
#41000000
1&
#41500000
0&
#42000000
1&
#42500000
0&
#43000000
1&
#43500000
0&
#44000000
1&
#44500000
0&
#45000000
1&
#45500000
0&
#45777000
1%
#46000000
1&
#46500000
0&
#47000000
1&
#47500000
0&
#48000000
1&
#48500000
0&
#49000000
1&
#49500000
0&
#50000000
1&
#50500000
0&
#51000000
1&
#51500000
0&
#52000000
1&
#52500000
0&
#53000000
1&
#53500000
0&
#54000000
1&
#54500000
0&
#55000000
1&
#55500000
0&
#56000000
1&
#56500000
0&
#57000000
1&
#57500000
0&
#58000000
1&
#58500000
0&
#59000000
1&
#59500000
0&
#60000000
1&
#60500000
0&
#61000000
1&
#61036000
0%
#61500000
0&
#62000000
1&
#62500000
0&
#63000000
1&
#63500000
0&
#64000000
1&
#64500000
0&
#65000000
1&
#65500000
0&
#66000000
1&
#66500000
0&
#67000000
1&
#67500000
0&
#68000000
1&
#68500000
0&
#69000000
1&
#69500000
0&
#70000000
1&
#70500000
0&
#71000000
1&
#71500000
0&
#72000000
1&
#72500000
0&
#73000000
1&
#73500000
0&
#74000000
1&
#74500000
0&
#75000000
1&
#75500000
0&
#76000000
1&
#76295000
1%
#76500000
0&
#77000000
1&
#77500000
0&
#78000000
1&
#78500000
0&
#79000000
1&
#79500000
0&
#80000000
1&
#80500000
0&
#81000000
1&
#81500000
0&
#82000000
1&
#82500000
0&
#83000000
1&
#83500000
0&
#84000000
1&
#84500000
0&
#85000000
1&
#85500000
0&
#86000000
1&
#86500000
0&
#87000000
1&
#87500000
0&
#88000000
1&
#88500000
0&
#89000000
1&
#89500000
0&
#90000000
1&
#90500000
0&
#91000000
1&
#91500000
0&
#91554000
0%
#92000000
1&
#92500000
0&
#93000000
1&
#93500000
0&
#94000000
1&
#94500000
0&
#95000000
1&
#95500000
0&
#96000000
1&
#96500000
0&
#97000000
1&
#97500000
0&
#98000000
1&
#98500000
0&
#99000000
1&
#99500000
0&
#100000000
1&
1'
#100500000
0&
#101000000
1&
#101500000
0&
#102000000
1&
#102500000
0&
#103000000
1&
#103500000
0&
#104000000
1&
#104500000
0&
#105000000
1&
#105500000
0&
#106000000
1&
#106500000
0&
#106813000
1%
#107000000
1&
#107500000
0&
#108000000
1&
#108500000
0&
#109000000
1&
#109500000
0&
#110000000
1&
#110500000
0&
#111000000
1&
#111500000
0&
#112000000
1&
#112500000
0&
#113000000
1&
#113500000
0&
#114000000
1&
#114500000
0&
#115000000
1&
#115500000
0&
#116000000
1&
#116500000
0&
#117000000
1&
#117500000
0&
#118000000
1&
#118500000
0&
#119000000
1&
#119500000
0&
#120000000
1&
#120500000
0&
#121000000
1&
#121500000
0&
#122000000
1&
#122072000
0%
#122500000
0&
#123000000
1&
#123500000
0&
#124000000
1&
#124500000
0&
#125000000
1&
#125500000
0&
#126000000
1&
#126500000
0&
#127000000
1&
#127500000
0&
#128000000
1&
#128500000
0&
#129000000
1&
#129500000
0&
#130000000
1&
#130500000
0&
#131000000
1&
#131500000
0&
#132000000
1&
#132500000
0&
#133000000
1&
#133500000
0&
#134000000
1&
#134500000
0&
#135000000
1&
#135500000
0&
#136000000
1&
#136500000
0&
#137000000
1&
#137331000
1%
#137500000
0&
#138000000
1&
#138500000
0&
#139000000
1&
#139500000
0&
#140000000
1&
#140500000
0&
#141000000
1&
#141500000
0&
#142000000
1&
#142500000
0&
#143000000
1&
#143500000
0&
#144000000
1&
#144500000
0&
#145000000
1&
#145500000
0&
#146000000
1&
#146500000
0&
#147000000
1&
#147500000
0&
#148000000
1&
#148500000
0&
#149000000
1&
#149500000
0&
#150000000
1&
#150500000
0&
#151000000
1&
#151500000
0&
#152000000
1&
#152500000
0&
#152590000
0%
#153000000
1&
#153500000
0&
#154000000
1&
#154500000
0&
#155000000
1&
#155500000
0&
#156000000
1&
#156500000
0&
#157000000
1&
#157500000
0&
#158000000
1&
#158500000
0&
#159000000
1&
#159500000
0&
#160000000
1&
#160500000
0&
#161000000
1&
#161500000
0&
#162000000
1&
#162500000
0&
#163000000
1&
#163500000
0&
#164000000
1&
#164500000
0&
#165000000
1&
#165500000
0&
#166000000
1&
#166500000
0&
#167000000
1&
#167500000
0&
#167849000
1%
#168000000
1&
#168500000
0&
#169000000
1&
#169500000
0&
#170000000
1&
#170500000
0&
#171000000
1&
#171500000
0&
#172000000
1&
#172500000
0&
#173000000
1&
#173500000
0&
#174000000
1&
#174500000
0&
#175000000
1&
#175500000
0&
#176000000
1&
#176500000
0&
#177000000
1&
#177500000
0&
#178000000
1&
#178500000
0&
#179000000
1&
#179500000
0&
#180000000
1&
#180500000
0&
#181000000
1&
#181500000
0&
#182000000
1&
#182500000
0&
#183000000
1&
#183108000
0%
#183500000
0&
#184000000
1&
#184500000
0&
#185000000
1&
#185500000
0&
#186000000
1&
#186500000
0&
#187000000
1&
#187500000
0&
#188000000
1&
#188500000
0&
#189000000
1&
#189500000
0&
#190000000
1&
#190500000
0&
#191000000
1&
#191500000
0&
#192000000
1&
#192500000
0&
#193000000
1&
#193500000
0&
#194000000
1&
#194500000
0&
#195000000
1&
#195500000
0&
#196000000
1&
#196500000
0&
#197000000
1&
#197500000
0&
#198000000
1&
#198367000
1%
#198500000
0&
#199000000
1&
#199500000
0&
#200000000
1&
#200500000
0&
#201000000
1&
#201500000
0&
#202000000
1&
#202500000
0&
#203000000
1&
#203500000
0&
#204000000
1&
#204500000
0&
#205000000
1&
#205500000
0&
#206000000
1&
#206500000
0&
#207000000
1&
#207500000
0&
#208000000
1&
#208500000
0&
#209000000
1&
#209500000
0&
#210000000
1&
#210500000
0&
#211000000
1&
#211500000
0&
#212000000
1&
#212500000
0&
#213000000
1&
#213500000
0&
#213626000
0%
#214000000
1&
#214500000
0&
#215000000
1&
#215500000
0&
#216000000
1&
#216500000
0&
#217000000
1&
#217500000
0&
#218000000
1&
#218500000
0&
#219000000
1&
#219500000
0&
#220000000
1&
#220500000
0&
#221000000
1&
#221500000
0&
#222000000
1&
#222500000
0&
#223000000
1&
#223500000
0&
#224000000
1&
#224500000
0&
#225000000
1&
#225500000
0&
#226000000
1&
#226500000
0&
#227000000
1&
#227500000
0&
#228000000
1&
#228500000
0&
#228885000
b1 F
17
1(
1%
#229000000
1&
#229500000
0&
#230000000
1&
#230500000
0&
#231000000
1&
#231500000
0&
#232000000
1&
#232500000
0&
#233000000
1&
#233500000
0&
#234000000
1&
#234500000
0&
#235000000
1&
#235500000
0&
#236000000
1&
#236500000
0&
#237000000
1&
#237500000
0&
#238000000
1&
#238500000
0&
#239000000
1&
#239500000
0&
#240000000
1&
#240500000
0&
#241000000
1&
#241500000
0&
#242000000
1&
#242500000
0&
#243000000
1&
#243500000
0&
#244000000
1&
#244144000
0%
#244500000
0&
#245000000
1&
#245500000
0&
#246000000
1&
#246500000
0&
#247000000
1&
#247500000
0&
#248000000
1&
#248500000
0&
#249000000
1&
#249500000
0&
#250000000
1&
#250500000
0&
#251000000
1&
#251500000
0&
#252000000
1&
#252500000
0&
#253000000
1&
#253500000
0&
#254000000
1&
#254500000
0&
#255000000
1&
#255500000
0&
#256000000
1&
#256500000
0&
#257000000
1&
#257500000
0&
#258000000
1&
#258500000
0&
#259000000
1&
#259403000
b1 9
b1 >
b1 ?
1<
18
b1 G
07
b10 F
0(
1%
#259500000
0<
0&
#260000000
b10 9
b10 >
b10 ?
1<
1&
#260500000
0<
0&
#261000000
b11 9
b11 >
b11 ?
1<
1&
#261500000
0<
0&
#262000000
b100 9
b100 >
b100 ?
1<
1&
#262500000
0<
0&
#263000000
b101 9
b101 >
b101 ?
1<
1&
#263500000
0<
0&
#264000000
b110 9
b110 >
b110 ?
1<
1&
#264500000
0<
0&
#265000000
b111 9
b111 >
b111 ?
1<
1&
#265500000
0<
0&
#266000000
b1000 9
b1000 >
b1000 ?
1<
1&
#266500000
0<
0&
#267000000
b1001 9
b1001 >
b1001 ?
1<
1&
#267500000
0<
0&
#268000000
b1010 9
b1010 >
b1010 ?
1<
1&
#268500000
0<
0&
#269000000
b1011 9
b1011 >
b1011 ?
1<
1&
#269500000
0<
0&
#270000000
b1100 9
b1100 >
b1100 ?
1<
1&
#270500000
0<
0&
#271000000
b1101 9
b1101 >
b1101 ?
1<
1&
#271500000
0<
0&
#272000000
b1110 9
b1110 >
b1110 ?
1<
1&
#272500000
0<
0&
#273000000
b1111 9
b1111 >
b1111 ?
1<
1&
#273500000
0<
0&
#274000000
b10000 9
b10000 >
b10000 ?
1<
1&
#274500000
0<
0&
#274662000
0%
#275000000
b10001 9
b10001 >
b10001 ?
1<
1&
#275500000
0<
0&
#276000000
b10010 9
b10010 >
b10010 ?
1<
1&
#276500000
0<
0&
#277000000
b10011 9
b10011 >
b10011 ?
1<
1&
#277500000
0<
0&
#278000000
b10100 9
b10100 >
b10100 ?
1<
1&
#278500000
0<
0&
#279000000
b10101 9
b10101 >
b10101 ?
1<
1&
#279500000
0<
0&
#280000000
b10110 9
b10110 >
b10110 ?
1<
1&
#280500000
0<
0&
#281000000
b10111 9
b10111 >
b10111 ?
1<
1&
#281500000
0<
0&
#282000000
b11000 9
b11000 >
b11000 ?
1<
1&
#282500000
0<
0&
#283000000
b11001 9
b11001 >
b11001 ?
1<
1&
#283500000
0<
0&
#284000000
b11010 9
b11010 >
b11010 ?
1<
1&
#284500000
0<
0&
#285000000
b11011 9
b11011 >
b11011 ?
1<
1&
#285500000
0<
0&
#286000000
b11100 9
b11100 >
b11100 ?
1<
1&
#286500000
0<
0&
#287000000
b11101 9
b11101 >
b11101 ?
1<
1&
#287500000
0<
0&
#288000000
b11110 9
b11110 >
b11110 ?
1<
1&
#288500000
0<
0&
#289000000
b11111 9
b11111 >
b11111 ?
1<
1&
#289500000
0<
0&
#289921000
b11 F
08
b10 G
1%
#290000000
1&
#290500000
0&
#291000000
1&
#291500000
0&
#292000000
1&
#292500000
0&
#293000000
1&
#293500000
0&
#294000000
1&
#294500000
0&
#295000000
1&
#295500000
0&
#296000000
1&
#296500000
0&
#297000000
1&
#297500000
0&
#298000000
1&
#298500000
0&
#299000000
1&
#299500000
0&
#300000000
1&
#300500000
0&
#301000000
1&
#301500000
0&
#302000000
1&
#302500000
0&
#303000000
1&
#303500000
0&
#304000000
1&
#304500000
0&
#305000000
1&
#305180000
0%
#305500000
0&
#306000000
1&
#306500000
0&
#307000000
1&
#307500000
0&
#308000000
1&
#308500000
0&
#309000000
1&
#309500000
0&
#310000000
1&
#310500000
0&
#311000000
1&
#311500000
0&
#312000000
1&
#312500000
0&
#313000000
1&
#313500000
0&
#314000000
1&
#314500000
0&
#315000000
1&
#315500000
0&
#316000000
1&
#316500000
0&
#317000000
1&
#317500000
0&
#318000000
1&
#318500000
0&
#319000000
1&
#319500000
0&
#320000000
1&
#320439000
r5 .
b1 ,
b11111 *
b0 F
1!
b11111 "
b11111 :
b11111 E
b11 G
1%
#320500000
0&
#321000000
1&
#321500000
0&
#322000000
1&
#322500000
0&
#323000000
1&
#323500000
0&
#324000000
1&
#324500000
0&
#325000000
1&
#325500000
0&
#326000000
1&
#326500000
0&
#327000000
1&
#327500000
0&
#328000000
1&
#328500000
0&
#329000000
1&
#329500000
0&
#330000000
1&
#330500000
0&
#331000000
1&
#331500000
0&
#332000000
1&
#332500000
0&
#333000000
1&
#333500000
0&
#334000000
1&
#334500000
0&
#335000000
1&
#335500000
0&
#335698000
0%
#336000000
1&
#336500000
0&
#337000000
1&
#337500000
0&
#338000000
1&
#338500000
0&
#339000000
1&
#339500000
0&
#340000000
1&
#340500000
0&
#341000000
1&
#341500000
0&
#342000000
1&
#342500000
0&
#343000000
1&
#343500000
0&
#344000000
1&
#344500000
0&
#345000000
1&
#345500000
0&
#346000000
1&
#346500000
0&
#347000000
1&
#347500000
0&
#348000000
1&
#348500000
0&
#349000000
1&
#349500000
0&
#350000000
1&
#350500000
0&
#350957000
b0 9
b0 >
b0 ?
17
0!
b0 G
1%
#351000000
1&
#351500000
0&
#352000000
1&
#352500000
0&
#353000000
1&
#353500000
0&
#354000000
1&
#354500000
0&
#355000000
1&
#355500000
0&
#356000000
1&
#356500000
0&
#357000000
1&
#357500000
0&
#358000000
1&
#358500000
0&
#359000000
1&
#359500000
0&
#360000000
1&
#360500000
0&
#361000000
1&
#361500000
0&
#362000000
1&
#362500000
0&
#363000000
1&
#363500000
0&
#364000000
1&
#364500000
0&
#365000000
1&
#365500000
0&
#366000000
1&
#366216000
0%
#366500000
0&
#367000000
1&
#367500000
0&
#368000000
1&
#368500000
0&
#369000000
1&
#369500000
0&
#370000000
1&
#370500000
0&
#371000000
1&
#371500000
0&
#372000000
1&
#372500000
0&
#373000000
1&
#373500000
0&
#374000000
1&
#374500000
0&
#375000000
1&
#375500000
0&
#376000000
1&
#376500000
0&
#377000000
1&
#377500000
0&
#378000000
1&
#378500000
0&
#379000000
1&
#379500000
0&
#380000000
1&
#380500000
0&
#381000000
1&
#381475000
1%
#381500000
0&
#382000000
1&
#382500000
0&
#383000000
1&
#383500000
0&
#384000000
1&
#384500000
0&
#385000000
1&
#385500000
0&
#386000000
1&
#386500000
0&
#387000000
1&
#387500000
0&
#388000000
1&
#388500000
0&
#389000000
1&
#389500000
0&
#390000000
1&
#390500000
0&
#391000000
1&
#391500000
0&
#392000000
1&
#392500000
0&
#393000000
1&
#393500000
0&
#394000000
1&
#394500000
0&
#395000000
1&
#395500000
0&
#396000000
1&
#396500000
0&
#396734000
0%
#397000000
1&
#397500000
0&
#398000000
1&
#398500000
0&
#399000000
1&
#399500000
0&
#400000000
1&
#400500000
0&
#401000000
1&
#401500000
0&
#402000000
1&
#402500000
0&
#403000000
1&
#403500000
0&
#404000000
1&
#404500000
0&
#405000000
1&
#405500000
0&
#406000000
1&
#406500000
0&
#407000000
1&
#407500000
0&
#408000000
1&
#408500000
0&
#409000000
1&
#409500000
0&
#410000000
1&
#410500000
0&
#411000000
1&
#411500000
0&
#411993000
1%
#412000000
1&
#412500000
0&
#413000000
1&
#413500000
0&
#414000000
1&
#414500000
0&
#415000000
1&
#415500000
0&
#416000000
1&
#416500000
0&
#417000000
1&
#417500000
0&
#418000000
1&
#418500000
0&
#419000000
1&
#419500000
0&
#420000000
1&
#420439000
r875 -
r500 3
r1000 2
r20 5
b100 1
r5 6
#420500000
0&
#420937000
1&
#421374000
0&
#421811000
1&
#422248000
0&
#422685000
1&
#423122000
0&
#423559000
1&
#423996000
0&
#424433000
1&
#424870000
0&
#425307000
1&
#425744000
0&
#426181000
1&
#426618000
0&
#427055000
1&
#427252000
0%
#427492000
0&
#427929000
1&
#428366000
0&
#428803000
1&
#429240000
0&
#429677000
1&
#430114000
0&
#430551000
1&
#430988000
0&
#431425000
1&
#431862000
0&
#432299000
1&
#432736000
0&
#433173000
1&
#433610000
0&
#434047000
1&
#434484000
0&
#434921000
1&
#435358000
0&
#435795000
1&
#436232000
0&
#436669000
1&
#437106000
0&
#437543000
1&
#437980000
0&
#438417000
1&
#438854000
0&
#439291000
1&
#439728000
0&
#440165000
1&
#440602000
0&
#441039000
1&
#441476000
0&
#441913000
1&
#442350000
0&
#442511000
b1 F
17
1(
1%
#442787000
1&
#443224000
0&
#443661000
1&
#444098000
0&
#444535000
1&
#444972000
0&
#445409000
1&
#445846000
0&
#446283000
1&
#446720000
0&
#447157000
1&
#447594000
0&
#448031000
1&
#448468000
0&
#448905000
1&
#449342000
0&
#449779000
1&
#450216000
0&
#450653000
1&
#451090000
0&
#451527000
1&
#451964000
0&
#452401000
1&
#452838000
0&
#453275000
1&
#453712000
0&
#454149000
1&
#454586000
0&
#455023000
1&
#455460000
0&
#455897000
1&
#456334000
0&
#456771000
1&
#457208000
0&
#457645000
1&
#457770000
0%
#458082000
0&
#458519000
1&
#458956000
0&
#459393000
1&
#459830000
0&
#460267000
1&
#460704000
0&
#461141000
1&
#461578000
0&
#462015000
1&
#462452000
0&
#462889000
1&
#463326000
0&
#463763000
1&
#464200000
0&
#464637000
1&
#465074000
0&
#465511000
1&
#465948000
0&
#466385000
1&
#466822000
0&
#467259000
1&
#467696000
0&
#468133000
1&
#468570000
0&
#469007000
1&
#469444000
0&
#469881000
1&
#470318000
0&
#470755000
1&
#471192000
0&
#471629000
1&
#472066000
0&
#472503000
1&
#472940000
0&
#473029000
18
b1 G
07
b10 F
0(
1%
#473377000
b1 9
b1 >
b1 ?
1<
1&
#473814000
0<
0&
#474251000
b10 9
b10 >
b10 ?
1<
1&
#474688000
0<
0&
#475125000
b11 9
b11 >
b11 ?
1<
1&
#475562000
0<
0&
#475999000
b100 9
b100 >
b100 ?
1<
1&
#476436000
0<
0&
#476873000
b101 9
b101 >
b101 ?
1<
1&
#477310000
0<
0&
#477747000
b110 9
b110 >
b110 ?
1<
1&
#478184000
0<
0&
#478621000
b111 9
b111 >
b111 ?
1<
1&
#479058000
0<
0&
#479495000
b1000 9
b1000 >
b1000 ?
1<
1&
#479932000
0<
0&
#480369000
b1001 9
b1001 >
b1001 ?
1<
1&
#480806000
0<
0&
#481243000
b1010 9
b1010 >
b1010 ?
1<
1&
#481680000
0<
0&
#482117000
b1011 9
b1011 >
b1011 ?
1<
1&
#482554000
0<
0&
#482991000
b1100 9
b1100 >
b1100 ?
1<
1&
#483428000
0<
0&
#483865000
b1101 9
b1101 >
b1101 ?
1<
1&
#484302000
0<
0&
#484739000
b1110 9
b1110 >
b1110 ?
1<
1&
#485176000
0<
0&
#485613000
b1111 9
b1111 >
b1111 ?
1<
1&
#486050000
0<
0&
#486487000
b10000 9
b10000 >
b10000 ?
1<
1&
#486924000
0<
0&
#487361000
b10001 9
b10001 >
b10001 ?
1<
1&
#487798000
0<
0&
#488235000
b10010 9
b10010 >
b10010 ?
1<
1&
#488288000
0%
#488672000
0<
0&
#489109000
b10011 9
b10011 >
b10011 ?
1<
1&
#489546000
0<
0&
#489983000
b10100 9
b10100 >
b10100 ?
1<
1&
#490420000
0<
0&
#490857000
b10101 9
b10101 >
b10101 ?
1<
1&
#491294000
0<
0&
#491731000
b10110 9
b10110 >
b10110 ?
1<
1&
#492168000
0<
0&
#492605000
b10111 9
b10111 >
b10111 ?
1<
1&
#493042000
0<
0&
#493479000
b11000 9
b11000 >
b11000 ?
1<
1&
#493916000
0<
0&
#494353000
b11001 9
b11001 >
b11001 ?
1<
1&
#494790000
0<
0&
#495227000
b11010 9
b11010 >
b11010 ?
1<
1&
#495664000
0<
0&
#496101000
b11011 9
b11011 >
b11011 ?
1<
1&
#496538000
0<
0&
#496975000
b11100 9
b11100 >
b11100 ?
1<
1&
#497412000
0<
0&
#497849000
b11101 9
b11101 >
b11101 ?
1<
1&
#498286000
0<
0&
#498723000
b11110 9
b11110 >
b11110 ?
1<
1&
#499160000
0<
0&
#499597000
b11111 9
b11111 >
b11111 ?
1<
1&
#500034000
0<
0&
#500471000
b100000 9
b100000 >
b100000 ?
1<
1&
#500908000
0<
0&
#501345000
b100001 9
b100001 >
b100001 ?
1<
1&
#501782000
0<
0&
#502219000
b100010 9
b100010 >
b100010 ?
1<
1&
#502656000
0<
0&
#503093000
b100011 9
b100011 >
b100011 ?
1<
1&
#503530000
0<
0&
#503547000
b11 F
08
b10 G
1%
#503967000
1&
#504404000
0&
#504841000
1&
#505278000
0&
#505715000
1&
#506152000
0&
#506589000
1&
#507026000
0&
#507463000
1&
#507900000
0&
#508337000
1&
#508774000
0&
#509211000
1&
#509648000
0&
#510085000
1&
#510522000
0&
#510959000
1&
#511396000
0&
#511833000
1&
#512270000
0&
#512707000
1&
#513144000
0&
#513581000
1&
#514018000
0&
#514455000
1&
#514892000
0&
#515329000
1&
#515766000
0&
#516203000
1&
